{
  "classic-english-pale-ale":{"vessel":"british-nonic","liquid":"amber","foam":"cream","primaryMotif":"barley-grain","secondaryMotif":"hop-leaf","composition":"left-right","accent":"malt-gold","clarity":"clear","fillLevel":"normal"},
  "american-pale-ale":{"vessel":"american-pint","liquid":"golden","foam":"regular-white","primaryMotif":"hop-cone","secondaryMotif":"citrus-slice","composition":"symmetric","accent":"hop-green","clarity":"clear","fillLevel":"normal"},
  "british-golden-ale":{"vessel":"british-nonic","liquid":"pale-gold","foam":"thin-white","primaryMotif":"barley-grain","secondaryMotif":"sparkle","composition":"single-left","accent":"gold","clarity":"clear","fillLevel":"normal"},
  "australian-sparkling-ale":{"vessel":"pilsner-glass","liquid":"golden","foam":"generous-white","primaryMotif":"sparkle","secondaryMotif":"barley-grain","composition":"low-crown","accent":"cyan","clarity":"clear","fillLevel":"high"},
  "new-zealand-pale-ale":{"vessel":"american-pint","liquid":"golden","foam":"regular-white","primaryMotif":"hop-cone","secondaryMotif":"pine-branch","composition":"back-left","accent":"hop-green","clarity":"clear","fillLevel":"normal"},
  "ipa":{"vessel":"tulip-glass","liquid":"deep-amber","foam":"regular-white","primaryMotif":"hop-cone","secondaryMotif":"hop-leaf","composition":"symmetric","accent":"hop-green","clarity":"clear","fillLevel":"normal"},
  "english-ipa":{"vessel":"british-nonic","liquid":"copper","foam":"cream","primaryMotif":"hop-leaf","secondaryMotif":"barley-grain","composition":"left-right","accent":"malt-gold","clarity":"clear","fillLevel":"normal"},
  "american-ipa":{"vessel":"american-pint","liquid":"orange","foam":"regular-white","primaryMotif":"hop-cone","secondaryMotif":"citrus-slice","composition":"back-right","accent":"hop-green","clarity":"clear","fillLevel":"normal"},
  "west-coast-ipa":{"vessel":"american-pint","liquid":"deep-amber","foam":"thin-white","primaryMotif":"hop-cone","secondaryMotif":"pine-branch","composition":"left-right","accent":"hop-green","clarity":"clear","fillLevel":"normal"},
  "new-england-ipa":{"vessel":"tulip-glass","liquid":"hazy-orange","foam":"generous-white","primaryMotif":"hop-cone","secondaryMotif":"citrus-slice","composition":"low-crown","accent":"citrus-gold","clarity":"hazy","fillLevel":"high"},
  "session-ipa":{"vessel":"pilsner-glass","liquid":"pale-gold","foam":"thin-white","primaryMotif":"hop-leaf","secondaryMotif":"sparkle","composition":"single-right","accent":"hop-green","clarity":"clear","fillLevel":"low"},
  "double-ipa":{"vessel":"snifter","liquid":"copper","foam":"generous-white","primaryMotif":"hop-cone","secondaryMotif":"sparkle","composition":"behind-vessel","accent":"gold","clarity":"clear","fillLevel":"high"},
  "black-ipa":{"vessel":"snifter","liquid":"black","foam":"beige","primaryMotif":"hop-cone","secondaryMotif":"coffee-beans","composition":"left-right","accent":"roasted-brown","clarity":"opaque","fillLevel":"normal"},
  "red-ipa":{"vessel":"tulip-glass","liquid":"ruby","foam":"cream","primaryMotif":"hop-cone","secondaryMotif":"citrus-slice","composition":"single-left","accent":"ruby","clarity":"clear","fillLevel":"normal"},
  "white-ipa":{"vessel":"weizen-glass","liquid":"hazy-straw","foam":"generous-white","primaryMotif":"wheat-ear","secondaryMotif":"hop-cone","composition":"symmetric","accent":"wheat-gold","clarity":"hazy","fillLevel":"high"},
  "belgian-ipa":{"vessel":"belgian-chalice","liquid":"orange","foam":"cream","primaryMotif":"yeast-cells","secondaryMotif":"hop-cone","composition":"behind-vessel","accent":"citrus-gold","clarity":"hazy","fillLevel":"normal"},
  "rye-ipa":{"vessel":"british-nonic","liquid":"copper","foam":"cream","primaryMotif":"barley-grain","secondaryMotif":"hop-cone","composition":"left-right","accent":"malt-gold","clarity":"clear","fillLevel":"normal"},
  "brown-ipa":{"vessel":"snifter","liquid":"brown","foam":"beige","primaryMotif":"hop-cone","secondaryMotif":"cacao-pod","composition":"back-left","accent":"roasted-brown","clarity":"opaque","fillLevel":"normal"},
  "witbier":{"vessel":"weizen-glass","liquid":"hazy-straw","foam":"generous-white","primaryMotif":"wheat-ear","secondaryMotif":"citrus-slice","composition":"low-crown","accent":"wheat-gold","clarity":"hazy","fillLevel":"high"},
  "india-pale-lager":{"vessel":"pilsner-glass","liquid":"pale-gold","foam":"thin-white","primaryMotif":"hop-cone","secondaryMotif":"barley-grain","composition":"symmetric","accent":"hop-green","clarity":"clear","fillLevel":"normal"}
}
